etherscan_api
