Metadata-Version: 2.4
Name: etherscan-api-v2
Version: 0.3
Summary: Etherscan v2 api client
Home-page: https://github.com/hanzhichao/etherscan-api
Author: Han Zhichao
Author-email: superhin@126.com
License: MIT license
Keywords: etherscan,eth,etherscan api,etherscan v2
Classifier: Programming Language :: Python
Classifier: Programming Language :: Python :: 3.7
License-File: LICENSE
Requires-Dist: requests
Requires-Dist: eth-abi
Dynamic: author
Dynamic: author-email
Dynamic: classifier
Dynamic: description
Dynamic: description-content-type
Dynamic: home-page
Dynamic: keywords
Dynamic: license
Dynamic: license-file
Dynamic: requires-dist
Dynamic: summary
